Metadata-Version: 2.1
Name: numba-special
Version: 0.2.0
Summary: Numba overloads for SciPy's special functions
Home-page: https://github.com/person142/numba_special
Author: Josh Wilson
License: UNKNOWN
Platform: UNKNOWN
